MANIFEST.in
setup.cfg
setup.py
sculpt/__init__.py
sculpt.model_tools.egg-info/PKG-INFO
sculpt.model_tools.egg-info/SOURCES.txt
sculpt.model_tools.egg-info/dependency_links.txt
sculpt.model_tools.egg-info/requires.txt
sculpt.model_tools.egg-info/top_level.txt
sculpt/model_tools/__init__.py
sculpt/model_tools/appuser_base.py
sculpt/model_tools/base.py
sculpt/model_tools/hash_generator.py
sculpt/model_tools/mixins.py
sculpt/model_tools/tools.py
sculpt/model_tools/view_mixins.py