Metadata-Version: 1.1
Name: sculpt.model-tools
Version: 0.1
Summary: A modest set of tools to work with Django models.
Home-page: https://github.com/damienjones/sculpt-model-tools
Author: Damien M. Jones
Author-email: damien@codesculpture.com
License: LGPLv2
Platform: UNKNOWN
Classifier: Development Status :: 3 - Alpha
Classifier: License :: OSI Approved :: GNU Lesser General Public License v2 (LGPLv2)
Classifier: Programming Language :: Python :: 2
Classifier: Programming Language :: Python :: 2.6
Classifier: Programming Language :: Python :: 2.7
